uowabc/__init__.py
uowabc/base.py
uowabc/sa/__init__.py
uowabc/sa/mixins.py
uowabc/sa/repository.py
uowabc/sa/uow.py
uow_abstractions-0.1.0.dist-info/LICENSE
uow_abstractions-0.1.0.dist-info/METADATA
uow_abstractions-0.1.0.dist-info/WHEEL
uow_abstractions-0.1.0.dist-info/RECORD
