Metadata-Version: 2.1
Name: uow-abstractions
Version: 0.1.0
Summary: Unit Of Work Abstractions
Home-page: https://projects.rocshers.com/open-source/uow-abstractions
License: MIT
Author: Aleksei Marusich
Author-email: aleksei.marusich@rocshers.com
Requires-Python: >=3.12,<4
Classifier: Intended Audience :: Developers
Classifier: License :: OSI Approved :: MIT License
Classifier: Programming Language :: Python
Classifier: Programming Language :: Python :: 3
Classifier: Programming Language :: Python :: 3.12
Classifier: Programming Language :: Python :: 3 :: Only
Classifier: Topic :: Software Development
Classifier: Topic :: Software Development :: Libraries
Classifier: Topic :: Software Development :: Libraries :: Python Modules
Classifier: Topic :: System :: Software Distribution
Project-URL: Repository, https://gitlab.com/rocshers/python/uow-abstractions
